{
  "label": "results_eft68_c6f20_c8f40_f791p902_mh125_Glauber_C6p37848_Lambda2000",
  "model_parameters": {
    "c6_over_f2_TeV2": 0.0,
    "c8_over_f4_TeV4": 0.0,
    "f_GeV": 791.9016202536699,
    "m_h": 125.0,
    "v": 246.0,
    "m_w": 80.36,
    "m_z": 91.19,
    "m_t": 173.1,
    "use_glauber_measure": true,
    "C_glauber": 6.378484848484849,
    "Lambda_glauber": 2000.0
  },
  "derived_tree_coefficients": {
    "glauber_scheme": "counterterm_subtracted",
    "lambda_tree": 0.12909808976138543,
    "mu2_tree_GeV2": 7812.5,
    "a0_mean_field": 0.3998252334093464,
    "glauber_t0": 0.09650009727272728,
    "glauber_lambda_shift": 0.0,
    "glauber_mu2_shift_after_lambda_GeV2": 0.0,
    "lambda_tree_raw_glauber_equivalent": -1.1333661913571575,
    "mu2_tree_raw_glauber_equivalent_GeV2": 646715.5959275449,
    "combo_TeV2": 0.0
  },
  "scan_parameters": {
    "T_min": 1.0,
    "T_max": 250.0,
    "phi_scan_range": [
      -10.0,
      791.9016202536699
    ],
    "n_phi_scan": 1200,
    "n_T_seeds": 3,
    "deltaX_target": 0.1,
    "x_eps": 0.001,
    "T_eps": 0.01,
    "deriv_order": 4,
    "phitol": 0.0001,
    "overlapAngle": 45.0,
    "Tn_Ttol": 0.01,
    "Tn_maxiter": 160,
    "include_zeroT_loops": true,
    "include_scalar_loops": true,
    "include_thermal": true,
    "include_scalar_thermal": true,
    "include_daisy": true,
    "renormalize_zeroT_loops": true,
    "thermal_approx": "spline"
  },
  "key_temperatures": {
    "Tn": 78.94461480873855,
    "Tc": 89.75571484192042,
    "Ts_false": 67.64125117187193,
    "Ts_true": 97.99084960937464,
    "S_at_Tn": 11047.70525692683,
    "S_over_Tn": 139.94248098736605,
    "false_phase_key": 1,
    "true_phase_key": 0,
    "phi_false_Tn": -0.001263801937508262,
    "phi_true_Tn": 228.9313946600774,
    "vTn_over_Tn": 2.8998988115239555,
    "Tc_minus_Tn_over_Tc": 0.12045026940315277
  },
  "gw_scales": {
    "gw_T_star_GeV": 78.94461480873855,
    "gw_alpha": 0.027792714580693215,
    "gw_beta_over_H": 1735.2431030145208,
    "gw_v_w": 1.0,
    "gw_g_star": 106.75
  },
  "gw_peaks": {
    "sw": {
      "f_peak_mHz": 26.122466354447656,
      "f_peak_Hz": 0.026122466354447656,
      "omega_peak": 7.07294069219203e-17
    },
    "turb": {
      "f_peak_mHz": 44.72415237382179,
      "f_peak_Hz": 0.04472415237382179,
      "omega_peak": 5.139406774487922e-21
    },
    "coll": {
      "f_peak_mHz": NaN,
      "f_peak_Hz": NaN,
      "omega_peak": NaN
    },
    "total": {
      "f_peak_mHz": 26.122466354447656,
      "f_peak_Hz": 0.026122466354447656,
      "omega_peak": 7.073390365968136e-17
    }
  },
  "gw_run_parameters": {
    "g_star": 106.75,
    "v_w": 1.0,
    "epsilon_turb": 1.0,
    "frequency_unit": "mHz"
  },
  "S3": 11061.275347800402,
  "S3_over_T": 140.1143748005976,
  "bounce_diagnostics": {
    "label": "results_eft68_c6f20_c8f40_f791p902_mh125_Glauber_C6p37848_Lambda2000",
    "C": NaN,
    "Lambda_GeV": NaN,
    "finiteT": null,
    "temperature_GeV": NaN,
    "phi_metaMin": -0.001263801937508262,
    "phi_absMin": 228.9313946600774,
    "phi_bar": 117.37195823184895,
    "phi_top": 79.40446082261438,
    "V(phi_meta)": -109008617.01081343,
    "V(phi_true)": -122842246.62175629,
    "V(phi_top)": -108078445.24940017,
    "DeltaV_true_minus_meta": -13833629.610942855,
    "r0": 3.3612019952701136e-06,
    "phi0": 223.74139837350552,
    "dphi0": -0.0498809260220745,
    "rscale_cubic": 0.03361201995270113,
    "rscale_curv": 0.03207555385745375,
    "wall_r_hi": 0.12516751741108884,
    "wall_thickness": 0.08700127538041638,
    "S_total": 11061.275347800402,
    "S_kin": 16592.830318729535,
    "S_pot": -5531.554970929132,
    "S_interior": 0.0,
    "S3_over_T": NaN,
    "beta_rscale": 29.751261644114248,
    "beta_curvature": 31.176403035017618,
    "beta_wall": 11.494084375515898,
    "Tn_from_transitionFinder_GeV": 78.94461480873855,
    "Tc_from_transitionFinder_GeV": 89.75571484192042,
    "T_spinodal_high_GeV": NaN,
    "T_spinodal_low_GeV": NaN,
    "gw_T_star_GeV": 78.94461480873855,
    "gw_alpha": 0.027792714580693215,
    "gw_beta_over_H": 1735.2431030145208,
    "gw_R_star_times_H": NaN,
    "gw_Gamma_Tstar_GeV4": NaN,
    "gw_dT_for_beta_GeV": NaN,
    "gw_f_sw_peak_Hz": NaN,
    "gw_f_turb_peak_Hz": NaN,
    "gw_f_coll_peak_Hz": NaN,
    "gw_g_star": 106.75,
    "gw_v_w": 1.0,
    "omega_sw_peak": NaN,
    "omega_turb_peak": NaN,
    "omega_coll_peak": NaN,
    "omega_tot_peak": NaN
  }
}